FlashFlask/__init__.py
FlashFlask/data.zip
FlashFlask/main.py
FlashFlask/licenses/0BSD.txt
FlashFlask/licenses/AFL-3.0.txt
FlashFlask/licenses/AGPL-3.0.txt
FlashFlask/licenses/Apache-2.0.txt
FlashFlask/licenses/Artistic-2.0.txt
FlashFlask/licenses/BSD-2-Clause.txt
FlashFlask/licenses/BSD-3-Clause-Clear.txt
FlashFlask/licenses/BSD-3-Clause.txt
FlashFlask/licenses/BSD-4-Clause.txt
FlashFlask/licenses/BSL-1.0.txt
FlashFlask/licenses/CC-BY-4.0.txt
FlashFlask/licenses/CC-BY-SA-4.0.txt
FlashFlask/licenses/CC0-1.0.txt
FlashFlask/licenses/ECL-2.0.txt
FlashFlask/licenses/EPL-1.0.txt
FlashFlask/licenses/EPL-2.0.txt
FlashFlask/licenses/EUPL-1.1.txt
FlashFlask/licenses/GPL-2.0.txt
FlashFlask/licenses/GPL-3.0.txt
FlashFlask/licenses/ISC.txt
FlashFlask/licenses/LGPL-2.1.txt
FlashFlask/licenses/LGPL-3.0.txt
FlashFlask/licenses/LPPL-1.3c.txt
FlashFlask/licenses/MIT.txt
FlashFlask/licenses/MPL-2.0.txt
FlashFlask/licenses/MS-PL.txt
FlashFlask/licenses/NCSA.txt
FlashFlask/licenses/OFL-1.1.txt
FlashFlask/licenses/OSL-3.0.txt
FlashFlask/licenses/PostgreSQL.txt
FlashFlask/licenses/Unlicense.txt
FlashFlask/licenses/WTFPL.txt
FlashFlask/licenses/Zlib.txt
FlashFlask-0.2.dist-info/METADATA
FlashFlask-0.2.dist-info/WHEEL
FlashFlask-0.2.dist-info/entry_points.txt
FlashFlask-0.2.dist-info/top_level.txt
FlashFlask-0.2.dist-info/RECORD
