Metadata-Version: 2.1
Name: FlashFlask
Version: 0.2
Requires-Dist: cs50 ==9.2.6
Requires-Dist: Flask ==3.0.0
Requires-Dist: flask-session ==0.5.0
Requires-Dist: Werkzeug ==3.0.1
Requires-Dist: requests
Requires-Dist: shutil
